[
    {
        "nombre": "Zona Curso - Girona",
        "latitud": 19.7117665,
        "longitud": -30.896627,
        "radio_peligro": 69,
        "radio_advertencia": 114
    },
    {
        "nombre": "Zona Sabe - Lleida",
        "latitud": -3.4176895,
        "longitud": -57.491169,
        "radio_peligro": 89,
        "radio_advertencia": 116
    },
    {
        "nombre": "Zona Llega - Valladolid",
        "latitud": -50.015906,
        "longitud": -116.437337,
        "radio_peligro": 51,
        "radio_advertencia": 95
    },
    {
        "nombre": "Zona Pueden - Sevilla",
        "latitud": -8.245568,
        "longitud": 113.761097,
        "radio_peligro": 58,
        "radio_advertencia": 105
    },
    {
        "nombre": "Zona Alguna - Vizcaya",
        "latitud": -10.2654825,
        "longitud": -168.535528,
        "radio_peligro": 67,
        "radio_advertencia": 91
    }
]